{"nodes": [{"id": "tools_native_sysroots_rdk_x5_usr_include_vtk_9_1_vtkwordcloud_h", "label": "vtkWordCloud.h", "file_type": "code", "source_file": "tools/native/sysroots/rdk-x5/usr/include/vtk-9.1/vtkWordCloud.h", "source_location": "L1"}, {"id": "vtkwordcloud_getadjustedsizes", "label": "GetAdjustedSizes()", "file_type": "code", "source_file": "tools/native/sysroots/rdk-x5/usr/include/vtk-9.1/vtkWordCloud.h", "source_location": "L208"}, {"id": "vtkwordcloud_setbackgroundcolorname", "label": "SetBackgroundColorName()", "file_type": "code", "source_file": "tools/native/sysroots/rdk-x5/usr/include/vtk-9.1/vtkWordCloud.h", "source_location": "L242"}, {"id": "vtkwordcloud_getbackgroundcolorname", "label": "GetBackgroundColorName()", "file_type": "code", "source_file": "tools/native/sysroots/rdk-x5/usr/include/vtk-9.1/vtkWordCloud.h", "source_location": "L250"}, {"id": "vtkwordcloud_setbwmask", "label": "SetBWMask()", "file_type": "code", "source_file": "tools/native/sysroots/rdk-x5/usr/include/vtk-9.1/vtkWordCloud.h", "source_location": "L258"}, {"id": "vtkwordcloud_getbwmask", "label": "GetBWMask()", "file_type": "code", "source_file": "tools/native/sysroots/rdk-x5/usr/include/vtk-9.1/vtkWordCloud.h", "source_location": "L266"}, {"id": "vtkwordcloud_setcolorschemename", "label": "SetColorSchemeName()", "file_type": "code", "source_file": "tools/native/sysroots/rdk-x5/usr/include/vtk-9.1/vtkWordCloud.h", "source_location": "L276"}, {"id": "vtkwordcloud_getcolorschemename", "label": "GetColorSchemeName()", "file_type": "code", "source_file": "tools/native/sysroots/rdk-x5/usr/include/vtk-9.1/vtkWordCloud.h", "source_location": "L284"}, {"id": "vtkwordcloud_setfilename", "label": "SetFileName()", "file_type": "code", "source_file": "tools/native/sysroots/rdk-x5/usr/include/vtk-9.1/vtkWordCloud.h", "source_location": "L303"}, {"id": "vtkwordcloud_getfilename", "label": "GetFileName()", "file_type": "code", "source_file": "tools/native/sysroots/rdk-x5/usr/include/vtk-9.1/vtkWordCloud.h", "source_location": "L311"}, {"id": "vtkwordcloud_setfontfilename", "label": "SetFontFileName()", "file_type": "code", "source_file": "tools/native/sysroots/rdk-x5/usr/include/vtk-9.1/vtkWordCloud.h", "source_location": "L320"}, {"id": "vtkwordcloud_getfontfilename", "label": "GetFontFileName()", "file_type": "code", "source_file": "tools/native/sysroots/rdk-x5/usr/include/vtk-9.1/vtkWordCloud.h", "source_location": "L328"}, {"id": "vtkwordcloud_setmaskcolorname", "label": "SetMaskColorName()", "file_type": "code", "source_file": "tools/native/sysroots/rdk-x5/usr/include/vtk-9.1/vtkWordCloud.h", "source_location": "L346"}, {"id": "vtkwordcloud_getmaskcolorname", "label": "GetMaskColorName()", "file_type": "code", "source_file": "tools/native/sysroots/rdk-x5/usr/include/vtk-9.1/vtkWordCloud.h", "source_location": "L354"}, {"id": "vtkwordcloud_setmaskfilename", "label": "SetMaskFileName()", "file_type": "code", "source_file": "tools/native/sysroots/rdk-x5/usr/include/vtk-9.1/vtkWordCloud.h", "source_location": "L367"}, {"id": "vtkwordcloud_getmaskfilename", "label": "GetMaskFileName()", "file_type": "code", "source_file": "tools/native/sysroots/rdk-x5/usr/include/vtk-9.1/vtkWordCloud.h", "source_location": "L375"}, {"id": "vtkwordcloud_getcolordistribution", "label": "GetColorDistribution()", "file_type": "code", "source_file": "tools/native/sysroots/rdk-x5/usr/include/vtk-9.1/vtkWordCloud.h", "source_location": "L419"}, {"id": "vtkwordcloud_getoffsetdistribution", "label": "GetOffsetDistribution()", "file_type": "code", "source_file": "tools/native/sysroots/rdk-x5/usr/include/vtk-9.1/vtkWordCloud.h", "source_location": "L429"}, {"id": "vtkwordcloud_getorientationdistribution", "label": "GetOrientationDistribution()", "file_type": "code", "source_file": "tools/native/sysroots/rdk-x5/usr/include/vtk-9.1/vtkWordCloud.h", "source_location": "L439"}, {"id": "vtkwordcloud_addorientation", "label": "AddOrientation()", "file_type": "code", "source_file": "tools/native/sysroots/rdk-x5/usr/include/vtk-9.1/vtkWordCloud.h", "source_location": "L452"}, {"id": "vtkwordcloud_getorientations", "label": "GetOrientations()", "file_type": "code", "source_file": "tools/native/sysroots/rdk-x5/usr/include/vtk-9.1/vtkWordCloud.h", "source_location": "L457"}, {"id": "vtkwordcloud_addreplacementpair", "label": "AddReplacementPair()", "file_type": "code", "source_file": "tools/native/sysroots/rdk-x5/usr/include/vtk-9.1/vtkWordCloud.h", "source_location": "L467"}, {"id": "vtkwordcloud_getreplacementpairs", "label": "GetReplacementPairs()", "file_type": "code", "source_file": "tools/native/sysroots/rdk-x5/usr/include/vtk-9.1/vtkWordCloud.h", "source_location": "L473"}, {"id": "vtkwordcloud_getsizes", "label": "GetSizes()", "file_type": "code", "source_file": "tools/native/sysroots/rdk-x5/usr/include/vtk-9.1/vtkWordCloud.h", "source_location": "L481"}, {"id": "vtkwordcloud_addstopword", "label": "AddStopWord()", "file_type": "code", "source_file": "tools/native/sysroots/rdk-x5/usr/include/vtk-9.1/vtkWordCloud.h", "source_location": "L491"}, {"id": "vtkwordcloud_clearstopwords", "label": "ClearStopWords()", "file_type": "code", "source_file": "tools/native/sysroots/rdk-x5/usr/include/vtk-9.1/vtkWordCloud.h", "source_location": "L496"}, {"id": "vtkwordcloud_getstopwords", "label": "GetStopWords()", "file_type": "code", "source_file": "tools/native/sysroots/rdk-x5/usr/include/vtk-9.1/vtkWordCloud.h", "source_location": "L501"}, {"id": "vtkwordcloud_setstoplistfilename", "label": "SetStopListFileName()", "file_type": "code", "source_file": "tools/native/sysroots/rdk-x5/usr/include/vtk-9.1/vtkWordCloud.h", "source_location": "L509"}, {"id": "vtkwordcloud_getstoplistfilename", "label": "GetStopListFileName()", "file_type": "code", "source_file": "tools/native/sysroots/rdk-x5/usr/include/vtk-9.1/vtkWordCloud.h", "source_location": "L517"}, {"id": "vtkwordcloud_settitle", "label": "SetTitle()", "file_type": "code", "source_file": "tools/native/sysroots/rdk-x5/usr/include/vtk-9.1/vtkWordCloud.h", "source_location": "L525"}, {"id": "vtkwordcloud_gettitle", "label": "GetTitle()", "file_type": "code", "source_file": "tools/native/sysroots/rdk-x5/usr/include/vtk-9.1/vtkWordCloud.h", "source_location": "L533"}, {"id": "vtkwordcloud_setwordcolorname", "label": "SetWordColorName()", "file_type": "code", "source_file": "tools/native/sysroots/rdk-x5/usr/include/vtk-9.1/vtkWordCloud.h", "source_location": "L542"}, {"id": "vtkwordcloud_getwordcolorname", "label": "GetWordColorName()", "file_type": "code", "source_file": "tools/native/sysroots/rdk-x5/usr/include/vtk-9.1/vtkWordCloud.h", "source_location": "L550"}, {"id": "vtkwordcloud_getkeptwords", "label": "GetKeptWords()", "file_type": "code", "source_file": "tools/native/sysroots/rdk-x5/usr/include/vtk-9.1/vtkWordCloud.h", "source_location": "L556"}, {"id": "vtkwordcloud_getskippedwords", "label": "GetSkippedWords()", "file_type": "code", "source_file": "tools/native/sysroots/rdk-x5/usr/include/vtk-9.1/vtkWordCloud.h", "source_location": "L564"}, {"id": "vtkwordcloud_getstoppedwords", "label": "GetStoppedWords()", "file_type": "code", "source_file": "tools/native/sysroots/rdk-x5/usr/include/vtk-9.1/vtkWordCloud.h", "source_location": "L571"}], "edges": [{"source": "tools_native_sysroots_rdk_x5_usr_include_vtk_9_1_vtkwordcloud_h", "target": "vtkimagealgorithm", "relation": "imports", "confidence": "EXTRACTED", "source_file": "tools/native/sysroots/rdk-x5/usr/include/vtk-9.1/vtkWordCloud.h", "source_location": "L18", "weight": 1.0}, {"source": "tools_native_sysroots_rdk_x5_usr_include_vtk_9_1_vtkwordcloud_h", "target": "vtkimagedata", "relation": "imports", "confidence": "EXTRACTED", "source_file": "tools/native/sysroots/rdk-x5/usr/include/vtk-9.1/vtkWordCloud.h", "source_location": "L19", "weight": 1.0}, {"source": "tools_native_sysroots_rdk_x5_usr_include_vtk_9_1_vtkwordcloud_h", "target": "vtkinfoviscoremodule", "relation": "imports", "confidence": "EXTRACTED", "source_file": "tools/native/sysroots/rdk-x5/usr/include/vtk-9.1/vtkWordCloud.h", "source_location": "L20", "weight": 1.0}, {"source": "tools_native_sysroots_rdk_x5_usr_include_vtk_9_1_vtkwordcloud_h", "target": "vtksmartpointer", "relation": "imports", "confidence": "EXTRACTED", "source_file": "tools/native/sysroots/rdk-x5/usr/include/vtk-9.1/vtkWordCloud.h", "source_location": "L21", "weight": 1.0}, {"source": "tools_native_sysroots_rdk_x5_usr_include_vtk_9_1_vtkwordcloud_h", "target": "array", "relation": "imports", "confidence": "EXTRACTED", "source_file": "tools/native/sysroots/rdk-x5/usr/include/vtk-9.1/vtkWordCloud.h", "source_location": "L23", "weight": 1.0}, {"source": "tools_native_sysroots_rdk_x5_usr_include_vtk_9_1_vtkwordcloud_h", "target": "functional", "relation": "imports", "confidence": "EXTRACTED", "source_file": "tools/native/sysroots/rdk-x5/usr/include/vtk-9.1/vtkWordCloud.h", "source_location": "L24", "weight": 1.0}, {"source": "tools_native_sysroots_rdk_x5_usr_include_vtk_9_1_vtkwordcloud_h", "target": "set", "relation": "imports", "confidence": "EXTRACTED", "source_file": "tools/native/sysroots/rdk-x5/usr/include/vtk-9.1/vtkWordCloud.h", "source_location": "L25", "weight": 1.0}, {"source": "tools_native_sysroots_rdk_x5_usr_include_vtk_9_1_vtkwordcloud_h", "target": "string", "relation": "imports", "confidence": "EXTRACTED", "source_file": "tools/native/sysroots/rdk-x5/usr/include/vtk-9.1/vtkWordCloud.h", "source_location": "L26", "weight": 1.0}, {"source": "tools_native_sysroots_rdk_x5_usr_include_vtk_9_1_vtkwordcloud_h", "target": "vector", "relation": "imports", "confidence": "EXTRACTED", "source_file": "tools/native/sysroots/rdk-x5/usr/include/vtk-9.1/vtkWordCloud.h", "source_location": "L27", "weight": 1.0}, {"source": "tools_native_sysroots_rdk_x5_usr_include_vtk_9_1_vtkwordcloud_h", "target": "vtkwordcloud_getadjustedsizes", "relation": "contains", "confidence": "EXTRACTED", "source_file": "tools/native/sysroots/rdk-x5/usr/include/vtk-9.1/vtkWordCloud.h", "source_location": "L208", "weight": 1.0}, {"source": "tools_native_sysroots_rdk_x5_usr_include_vtk_9_1_vtkwordcloud_h", "target": "vtkwordcloud_setbackgroundcolorname", "relation": "contains", "confidence": "EXTRACTED", "source_file": "tools/native/sysroots/rdk-x5/usr/include/vtk-9.1/vtkWordCloud.h", "source_location": "L242", "weight": 1.0}, {"source": "tools_native_sysroots_rdk_x5_usr_include_vtk_9_1_vtkwordcloud_h", "target": "vtkwordcloud_getbackgroundcolorname", "relation": "contains", "confidence": "EXTRACTED", "source_file": "tools/native/sysroots/rdk-x5/usr/include/vtk-9.1/vtkWordCloud.h", "source_location": "L250", "weight": 1.0}, {"source": "tools_native_sysroots_rdk_x5_usr_include_vtk_9_1_vtkwordcloud_h", "target": "vtkwordcloud_setbwmask", "relation": "contains", "confidence": "EXTRACTED", "source_file": "tools/native/sysroots/rdk-x5/usr/include/vtk-9.1/vtkWordCloud.h", "source_location": "L258", "weight": 1.0}, {"source": "tools_native_sysroots_rdk_x5_usr_include_vtk_9_1_vtkwordcloud_h", "target": "vtkwordcloud_getbwmask", "relation": "contains", "confidence": "EXTRACTED", "source_file": "tools/native/sysroots/rdk-x5/usr/include/vtk-9.1/vtkWordCloud.h", "source_location": "L266", "weight": 1.0}, {"source": "tools_native_sysroots_rdk_x5_usr_include_vtk_9_1_vtkwordcloud_h", "target": "vtkwordcloud_setcolorschemename", "relation": "contains", "confidence": "EXTRACTED", "source_file": "tools/native/sysroots/rdk-x5/usr/include/vtk-9.1/vtkWordCloud.h", "source_location": "L276", "weight": 1.0}, {"source": "tools_native_sysroots_rdk_x5_usr_include_vtk_9_1_vtkwordcloud_h", "target": "vtkwordcloud_getcolorschemename", "relation": "contains", "confidence": "EXTRACTED", "source_file": "tools/native/sysroots/rdk-x5/usr/include/vtk-9.1/vtkWordCloud.h", "source_location": "L284", "weight": 1.0}, {"source": "tools_native_sysroots_rdk_x5_usr_include_vtk_9_1_vtkwordcloud_h", "target": "vtkwordcloud_setfilename", "relation": "contains", "confidence": "EXTRACTED", "source_file": "tools/native/sysroots/rdk-x5/usr/include/vtk-9.1/vtkWordCloud.h", "source_location": "L303", "weight": 1.0}, {"source": "tools_native_sysroots_rdk_x5_usr_include_vtk_9_1_vtkwordcloud_h", "target": "vtkwordcloud_getfilename", "relation": "contains", "confidence": "EXTRACTED", "source_file": "tools/native/sysroots/rdk-x5/usr/include/vtk-9.1/vtkWordCloud.h", "source_location": "L311", "weight": 1.0}, {"source": "tools_native_sysroots_rdk_x5_usr_include_vtk_9_1_vtkwordcloud_h", "target": "vtkwordcloud_setfontfilename", "relation": "contains", "confidence": "EXTRACTED", "source_file": "tools/native/sysroots/rdk-x5/usr/include/vtk-9.1/vtkWordCloud.h", "source_location": "L320", "weight": 1.0}, {"source": "tools_native_sysroots_rdk_x5_usr_include_vtk_9_1_vtkwordcloud_h", "target": "vtkwordcloud_getfontfilename", "relation": "contains", "confidence": "EXTRACTED", "source_file": "tools/native/sysroots/rdk-x5/usr/include/vtk-9.1/vtkWordCloud.h", "source_location": "L328", "weight": 1.0}, {"source": "tools_native_sysroots_rdk_x5_usr_include_vtk_9_1_vtkwordcloud_h", "target": "vtkwordcloud_setmaskcolorname", "relation": "contains", "confidence": "EXTRACTED", "source_file": "tools/native/sysroots/rdk-x5/usr/include/vtk-9.1/vtkWordCloud.h", "source_location": "L346", "weight": 1.0}, {"source": "tools_native_sysroots_rdk_x5_usr_include_vtk_9_1_vtkwordcloud_h", "target": "vtkwordcloud_getmaskcolorname", "relation": "contains", "confidence": "EXTRACTED", "source_file": "tools/native/sysroots/rdk-x5/usr/include/vtk-9.1/vtkWordCloud.h", "source_location": "L354", "weight": 1.0}, {"source": "tools_native_sysroots_rdk_x5_usr_include_vtk_9_1_vtkwordcloud_h", "target": "vtkwordcloud_setmaskfilename", "relation": "contains", "confidence": "EXTRACTED", "source_file": "tools/native/sysroots/rdk-x5/usr/include/vtk-9.1/vtkWordCloud.h", "source_location": "L367", "weight": 1.0}, {"source": "tools_native_sysroots_rdk_x5_usr_include_vtk_9_1_vtkwordcloud_h", "target": "vtkwordcloud_getmaskfilename", "relation": "contains", "confidence": "EXTRACTED", "source_file": "tools/native/sysroots/rdk-x5/usr/include/vtk-9.1/vtkWordCloud.h", "source_location": "L375", "weight": 1.0}, {"source": "tools_native_sysroots_rdk_x5_usr_include_vtk_9_1_vtkwordcloud_h", "target": "vtkwordcloud_getcolordistribution", "relation": "contains", "confidence": "EXTRACTED", "source_file": "tools/native/sysroots/rdk-x5/usr/include/vtk-9.1/vtkWordCloud.h", "source_location": "L419", "weight": 1.0}, {"source": "tools_native_sysroots_rdk_x5_usr_include_vtk_9_1_vtkwordcloud_h", "target": "vtkwordcloud_getoffsetdistribution", "relation": "contains", "confidence": "EXTRACTED", "source_file": "tools/native/sysroots/rdk-x5/usr/include/vtk-9.1/vtkWordCloud.h", "source_location": "L429", "weight": 1.0}, {"source": "tools_native_sysroots_rdk_x5_usr_include_vtk_9_1_vtkwordcloud_h", "target": "vtkwordcloud_getorientationdistribution", "relation": "contains", "confidence": "EXTRACTED", "source_file": "tools/native/sysroots/rdk-x5/usr/include/vtk-9.1/vtkWordCloud.h", "source_location": "L439", "weight": 1.0}, {"source": "tools_native_sysroots_rdk_x5_usr_include_vtk_9_1_vtkwordcloud_h", "target": "vtkwordcloud_addorientation", "relation": "contains", "confidence": "EXTRACTED", "source_file": "tools/native/sysroots/rdk-x5/usr/include/vtk-9.1/vtkWordCloud.h", "source_location": "L452", "weight": 1.0}, {"source": "tools_native_sysroots_rdk_x5_usr_include_vtk_9_1_vtkwordcloud_h", "target": "vtkwordcloud_getorientations", "relation": "contains", "confidence": "EXTRACTED", "source_file": "tools/native/sysroots/rdk-x5/usr/include/vtk-9.1/vtkWordCloud.h", "source_location": "L457", "weight": 1.0}, {"source": "tools_native_sysroots_rdk_x5_usr_include_vtk_9_1_vtkwordcloud_h", "target": "vtkwordcloud_addreplacementpair", "relation": "contains", "confidence": "EXTRACTED", "source_file": "tools/native/sysroots/rdk-x5/usr/include/vtk-9.1/vtkWordCloud.h", "source_location": "L467", "weight": 1.0}, {"source": "tools_native_sysroots_rdk_x5_usr_include_vtk_9_1_vtkwordcloud_h", "target": "vtkwordcloud_getreplacementpairs", "relation": "contains", "confidence": "EXTRACTED", "source_file": "tools/native/sysroots/rdk-x5/usr/include/vtk-9.1/vtkWordCloud.h", "source_location": "L473", "weight": 1.0}, {"source": "tools_native_sysroots_rdk_x5_usr_include_vtk_9_1_vtkwordcloud_h", "target": "vtkwordcloud_getsizes", "relation": "contains", "confidence": "EXTRACTED", "source_file": "tools/native/sysroots/rdk-x5/usr/include/vtk-9.1/vtkWordCloud.h", "source_location": "L481", "weight": 1.0}, {"source": "tools_native_sysroots_rdk_x5_usr_include_vtk_9_1_vtkwordcloud_h", "target": "vtkwordcloud_addstopword", "relation": "contains", "confidence": "EXTRACTED", "source_file": "tools/native/sysroots/rdk-x5/usr/include/vtk-9.1/vtkWordCloud.h", "source_location": "L491", "weight": 1.0}, {"source": "tools_native_sysroots_rdk_x5_usr_include_vtk_9_1_vtkwordcloud_h", "target": "vtkwordcloud_clearstopwords", "relation": "contains", "confidence": "EXTRACTED", "source_file": "tools/native/sysroots/rdk-x5/usr/include/vtk-9.1/vtkWordCloud.h", "source_location": "L496", "weight": 1.0}, {"source": "tools_native_sysroots_rdk_x5_usr_include_vtk_9_1_vtkwordcloud_h", "target": "vtkwordcloud_getstopwords", "relation": "contains", "confidence": "EXTRACTED", "source_file": "tools/native/sysroots/rdk-x5/usr/include/vtk-9.1/vtkWordCloud.h", "source_location": "L501", "weight": 1.0}, {"source": "tools_native_sysroots_rdk_x5_usr_include_vtk_9_1_vtkwordcloud_h", "target": "vtkwordcloud_setstoplistfilename", "relation": "contains", "confidence": "EXTRACTED", "source_file": "tools/native/sysroots/rdk-x5/usr/include/vtk-9.1/vtkWordCloud.h", "source_location": "L509", "weight": 1.0}, {"source": "tools_native_sysroots_rdk_x5_usr_include_vtk_9_1_vtkwordcloud_h", "target": "vtkwordcloud_getstoplistfilename", "relation": "contains", "confidence": "EXTRACTED", "source_file": "tools/native/sysroots/rdk-x5/usr/include/vtk-9.1/vtkWordCloud.h", "source_location": "L517", "weight": 1.0}, {"source": "tools_native_sysroots_rdk_x5_usr_include_vtk_9_1_vtkwordcloud_h", "target": "vtkwordcloud_settitle", "relation": "contains", "confidence": "EXTRACTED", "source_file": "tools/native/sysroots/rdk-x5/usr/include/vtk-9.1/vtkWordCloud.h", "source_location": "L525", "weight": 1.0}, {"source": "tools_native_sysroots_rdk_x5_usr_include_vtk_9_1_vtkwordcloud_h", "target": "vtkwordcloud_gettitle", "relation": "contains", "confidence": "EXTRACTED", "source_file": "tools/native/sysroots/rdk-x5/usr/include/vtk-9.1/vtkWordCloud.h", "source_location": "L533", "weight": 1.0}, {"source": "tools_native_sysroots_rdk_x5_usr_include_vtk_9_1_vtkwordcloud_h", "target": "vtkwordcloud_setwordcolorname", "relation": "contains", "confidence": "EXTRACTED", "source_file": "tools/native/sysroots/rdk-x5/usr/include/vtk-9.1/vtkWordCloud.h", "source_location": "L542", "weight": 1.0}, {"source": "tools_native_sysroots_rdk_x5_usr_include_vtk_9_1_vtkwordcloud_h", "target": "vtkwordcloud_getwordcolorname", "relation": "contains", "confidence": "EXTRACTED", "source_file": "tools/native/sysroots/rdk-x5/usr/include/vtk-9.1/vtkWordCloud.h", "source_location": "L550", "weight": 1.0}, {"source": "tools_native_sysroots_rdk_x5_usr_include_vtk_9_1_vtkwordcloud_h", "target": "vtkwordcloud_getkeptwords", "relation": "contains", "confidence": "EXTRACTED", "source_file": "tools/native/sysroots/rdk-x5/usr/include/vtk-9.1/vtkWordCloud.h", "source_location": "L556", "weight": 1.0}, {"source": "tools_native_sysroots_rdk_x5_usr_include_vtk_9_1_vtkwordcloud_h", "target": "vtkwordcloud_getskippedwords", "relation": "contains", "confidence": "EXTRACTED", "source_file": "tools/native/sysroots/rdk-x5/usr/include/vtk-9.1/vtkWordCloud.h", "source_location": "L564", "weight": 1.0}, {"source": "tools_native_sysroots_rdk_x5_usr_include_vtk_9_1_vtkwordcloud_h", "target": "vtkwordcloud_getstoppedwords", "relation": "contains", "confidence": "EXTRACTED", "source_file": "tools/native/sysroots/rdk-x5/usr/include/vtk-9.1/vtkWordCloud.h", "source_location": "L571", "weight": 1.0}]}